<?xml version="1.0" encoding="utf-8" ?>
<dwsync>
<file name="head.sub.php" server="115.68.29.101/public_html/" local="131356704600000000" remote="131356704600000000" Dst="0" />
<file name="shop.index.php" server="115.68.29.101/public_html/" local="131356704600000000" remote="131356704600000000" Dst="0" />
<file name="shop.tail.php" server="115.68.29.101/public_html/" local="131359362146028215" remote="131359362170000000" Dst="0" />
<file name="tail.sub.php" server="115.68.29.101/public_html/" local="131356704600000000" remote="131356704600000000" Dst="0" />
<file name="shop.head.php" server="115.68.29.101/public_html/" local="131395231513812054" remote="131395231540000000" Dst="0" />
<file name="wing.php" server="115.68.29.101/public_html/" local="131356775410000000" remote="131356775450000000" Dst="0" />
<file name="menu-m.php" server="115.68.29.101/public_html/" local="131356704600000000" remote="131356704600000000" Dst="0" />
<file name="menu.php" server="115.68.29.101/public_html/" local="131356704600000000" remote="131356704600000000" Dst="0" />
</dwsync>